{
  "kind": "singleType",
  "collectionName": "profiles",
  "info": {
    "singularName": "profile",
    "pluralName": "profiles",
    "displayName": "Profile",
    "description": "Main profile information for the resume website"
  },
  "options": {
    "draftAndPublish": true
  },
  "pluginOptions": {},
  "attributes": {
    "firstName": {
      "type": "string",
      "required": true
    },
    "lastName": {
      "type": "string",
      "required": true
    },
    "initials": {
      "type": "string",
      "maxLength": 5
    },
    "title": {
      "type": "string",
      "required": true
    },
    "subtitle": {
      "type": "string"
    },
    "bio": {
      "type": "richtext"
    },
    "email": {
      "type": "email",
      "required": true
    },
    "phone": {
      "type": "string"
    },
    "location": {
      "type": "string"
    },
    "heroStats": {
      "type": "json"
    },
    "heroBadges": {
      "type": "json"
    },
    "socialLinks": {
      "type": "json"
    },
    "timelineSteps": {
      "type": "json"
    },
    "tagline": {
      "type": "text"
    },
    "profilePhoto": {
      "type": "media",
      "multiple": false,
      "allowedTypes": [
        "images"
      ]
    },
    "resumePDF": {
      "type": "media",
      "multiple": false,
      "allowedTypes": [
        "files"
      ]
    },
    "resumeText": {
      "type": "media",
      "multiple": false,
      "allowedTypes": [
        "files"
      ]
    },
    "resumeLastUpdated": {
      "type": "string"
    }
  }
}